databarge/__init__.py
databarge/connections.py
databarge/dimensions.py
databarge/execution.py
databarge/functions.py
databarge/transfers.py
databarge-2.0.4.dist-info/LICENSE
databarge-2.0.4.dist-info/METADATA
databarge-2.0.4.dist-info/WHEEL
databarge-2.0.4.dist-info/top_level.txt
databarge-2.0.4.dist-info/RECORD
