Metadata-Version: 2.1
Name: databarge
Version: 2.0.4
Summary: Simple ETL tools for SQL Server
Home-page: https://github.com/porteverte/databarge
Author: Porte Verte
Author-email: Port Verte <porte_verte@outlook.com>
Project-URL: Homepage, https://github.com/porteverte/databarge
Project-URL: Issues, https://github.com/porteverte/databarge/issues
Classifier: Programming Language :: Python :: 3
Classifier: License :: OSI Approved :: MIT License
Classifier: Operating System :: OS Independent
Requires-Python: >=3.8
License-File: LICENSE
